subscriptions/__init__.py
subscriptions/admin.py
subscriptions/defaults.py
subscriptions/exceptions.py
subscriptions/fields.py
subscriptions/functions.py
subscriptions/logging.py
subscriptions/metrics.py
subscriptions/middleware.py
subscriptions/models.py
subscriptions/reports.py
subscriptions/signals.py
subscriptions/tasks.py
subscriptions/urls.py
subscriptions/utils.py
subscriptions/validators.py
subscriptions/views.py
subscriptions/__pycache__/__init__.cpython-310.pyc
subscriptions/__pycache__/__init__.cpython-39.pyc
subscriptions/__pycache__/admin.cpython-39.pyc
subscriptions/__pycache__/defaults.cpython-39.pyc
subscriptions/__pycache__/exceptions.cpython-39.pyc
subscriptions/__pycache__/fields.cpython-310.pyc
subscriptions/__pycache__/fields.cpython-39.pyc
subscriptions/__pycache__/functions.cpython-39.pyc
subscriptions/__pycache__/helpers.cpython-39.pyc
subscriptions/__pycache__/middleware.cpython-39.pyc
subscriptions/__pycache__/models.cpython-310.pyc
subscriptions/__pycache__/models.cpython-39.pyc
subscriptions/__pycache__/signals.cpython-39.pyc
subscriptions/__pycache__/urls.cpython-39.pyc
subscriptions/__pycache__/utils.cpython-39.pyc
subscriptions/__pycache__/views.cpython-39.pyc
subscriptions/api/fields.py
subscriptions/api/serializers.py
subscriptions/api/urls.py
subscriptions/api/views.py
subscriptions/api/__pycache__/fields.cpython-39.pyc
subscriptions/api/__pycache__/serializers.cpython-39.pyc
subscriptions/api/__pycache__/urls.cpython-39.pyc
subscriptions/api/__pycache__/views.cpython-39.pyc
subscriptions/management/commands/check_unfinished_payments.py
subscriptions/migrations/0001_initial.py
subscriptions/migrations/0002_subscriptionpayment_metadata_and_more.py
subscriptions/migrations/0003_remove_subscriptionpayment_subscription_charge_date_and_more.py
subscriptions/migrations/0004_remove_plan_unique_plan_slug_remove_plan_slug.py
subscriptions/migrations/0005_alter_subscriptionpayment_metadata_and_more.py
django_subscriptions_rt-1.0.3.dist-info/METADATA
django_subscriptions_rt-1.0.3.dist-info/WHEEL
django_subscriptions_rt-1.0.3.dist-info/top_level.txt
django_subscriptions_rt-1.0.3.dist-info/RECORD
