Metadata-Version: 2.1
Name: django-subscriptions-rt
Version: 1.0.3
Summary: Subscriptions and payments for your django app
Home-page: https://github.com/reef-technologies/django-subscriptions-rt
Author: Aleksandr Goncharov
Author-email: aleksandr.goncharov@reef.pl
Classifier: Programming Language :: Python :: 3
Classifier: Operating System :: OS Independent
Requires-Python: >=3.9
Requires-Dist: django (<4.3,>=3.2)
Requires-Dist: django-money (<3.2,>=3.0)
Requires-Dist: more-itertools (<10,>=8.8.0)
Requires-Dist: python-dateutil (<2.9,>=2.8.2)
Requires-Dist: djangorestframework (<3.15,>=3.14)
Requires-Dist: requests (<3.0,>=2.26.0)
Requires-Dist: tenacity (<9.0,>=8.0)
Requires-Dist: pydantic (<1.11,>=1.10)
Provides-Extra: apple_in_app
Requires-Dist: PyJWT (<3,>=2.6) ; extra == 'apple_in_app'
Requires-Dist: pyOpenSSL (<24,>=23.2) ; extra == 'apple_in_app'
Requires-Dist: cryptography (>=41.0.1) ; extra == 'apple_in_app'
Provides-Extra: default_plan
Requires-Dist: django-constance[database] (<3,>=2.9.0) ; extra == 'default_plan'
Provides-Extra: google_in_app
Requires-Dist: google-api-python-client (<3,>=2.88.0) ; extra == 'google_in_app'
Requires-Dist: oauth2client (==4.1.3) ; extra == 'google_in_app'
